{
  "date": "2026-06-05",
  "strategy_1": [
    {
      "stock_id": "3231",
      "yoys": [
        141.6,
        151.5,
        177.4
      ],
      "pos_count": 3,
      "latest_rev": 284893080000.0,
      "accel": 25.900000000000006,
      "rev_score": 14,
      "price": 171.0,
      "price_chg": 34.1,
      "above_ma20": true,
      "above_ma60": true,
      "ma_bonus": 6,
      "total_score": 20,
      "name": "緯創"
    },
    {
      "stock_id": "8112",
      "yoys": [
        32.3,
        72.5,
        136.8
      ],
      "pos_count": 3,
      "latest_rev": 31218239000.0,
      "accel": 64.30000000000001,
      "rev_score": 14,
      "price": 92.6,
      "price_chg": 31.0,
      "above_ma20": true,
      "above_ma60": true,
      "ma_bonus": 6,
      "total_score": 20,
      "name": "至上"
    },
    {
      "stock_id": "2425",
      "yoys": [
        26.6,
        43.9,
        113.5
      ],
      "pos_count": 3,
      "latest_rev": 1001646000.0,
      "accel": 69.6,
      "rev_score": 13,
      "price": 35.45,
      "price_chg": 23.5,
      "above_ma20": true,
      "above_ma60": true,
      "ma_bonus": 6,
      "total_score": 19,
      "name": "承啟"
    },
    {
      "stock_id": "2360",
      "yoys": [
        59.3,
        72.1,
        86.0
      ],
      "pos_count": 3,
      "latest_rev": 3826300000.0,
      "accel": 13.900000000000006,
      "rev_score": 12,
      "price": 2565.0,
      "price_chg": 163.3,
      "above_ma20": true,
      "above_ma60": true,
      "ma_bonus": 6,
      "total_score": 18,
      "name": "致茂"
    },
    {
      "stock_id": "2404",
      "yoys": [
        41.3,
        58.9,
        68.9
      ],
      "pos_count": 3,
      "latest_rev": 7279091000.0,
      "accel": 10.000000000000007,
      "rev_score": 12,
      "price": 1205.0,
      "price_chg": 29.4,
      "above_ma20": true,
      "above_ma60": true,
      "ma_bonus": 6,
      "total_score": 18,
      "name": "漢唐"
    }
  ],
  "strategy_2": [
    {
      "stock_id": "8215",
      "name": "明基材",
      "total_score": 17,
      "score_detail": "A9+B4+D4",
      "tvr": 2240.7,
      "buy_days": 5,
      "consec": 4,
      "conc_20": 413.5,
      "foreign_5d": 3167517.0,
      "trust_5d": 314000.0,
      "price": 29.65,
      "above_ma20": true,
      "above_ma60": true,
      "vol_ratio": 1.85
    },
    {
      "stock_id": "1723",
      "name": "中碳",
      "total_score": 16,
      "score_detail": "A9+B4+D3",
      "tvr": 2545.4,
      "buy_days": 5,
      "consec": 4,
      "conc_20": 2985.4,
      "foreign_5d": 218708.0,
      "trust_5d": 104000.0,
      "price": 85.3,
      "above_ma20": true,
      "above_ma60": true,
      "vol_ratio": 1.26
    },
    {
      "stock_id": "2492",
      "name": "華新科",
      "total_score": 16,
      "score_detail": "A10+B4+D2",
      "tvr": 6431.9,
      "buy_days": 10,
      "consec": 10,
      "conc_20": 2739.1,
      "foreign_5d": 5099996.0,
      "trust_5d": 1573000.0,
      "price": 416.0,
      "above_ma20": true,
      "above_ma60": true,
      "vol_ratio": 0.36
    },
    {
      "stock_id": "9933",
      "name": "中鼎",
      "total_score": 16,
      "score_detail": "A9+B3+D4",
      "tvr": 1645.1,
      "buy_days": 5,
      "consec": 4,
      "conc_20": 671.2,
      "foreign_5d": 9858410.0,
      "trust_5d": 366400.0,
      "price": 43.45,
      "above_ma20": true,
      "above_ma60": true,
      "vol_ratio": 1.51
    },
    {
      "stock_id": "1303",
      "name": "南亞",
      "total_score": 15,
      "score_detail": "A9+B3+D3",
      "tvr": 2969.7,
      "buy_days": 9,
      "consec": 8,
      "conc_20": 799.8,
      "foreign_5d": 31474569.0,
      "trust_5d": 10765423.0,
      "price": 104.5,
      "above_ma20": true,
      "above_ma60": true,
      "vol_ratio": 1.18
    }
  ],
  "strategy_3": [
    {
      "stock_id": "6890",
      "name": "來億-KY",
      "total_score": 10,
      "score_detail": "A0+B4+C3+D3",
      "big_holder_pct": 1.8,
      "big_holder_chg": -0.64,
      "margin_chg": -301,
      "short_chg": 85,
      "inst_ratio": 19558.8,
      "price": 242.5,
      "above_ma20": true
    },
    {
      "stock_id": "1718",
      "name": "中纖",
      "total_score": 8,
      "score_detail": "A0+B2+C3+D3",
      "big_holder_pct": 6.1,
      "big_holder_chg": 0.15,
      "margin_chg": 5326,
      "short_chg": 305,
      "inst_ratio": 5242.8,
      "price": 9.85,
      "above_ma20": true
    },
    {
      "stock_id": "6517",
      "name": "保勝光學",
      "total_score": 8,
      "score_detail": "A0+B2+C3+D3",
      "big_holder_pct": 1.8,
      "big_holder_chg": 0.1,
      "margin_chg": -23,
      "short_chg": -2,
      "inst_ratio": 6622.8,
      "price": 69.3,
      "above_ma20": true
    },
    {
      "stock_id": "1714",
      "name": "和桐",
      "total_score": 8,
      "score_detail": "A0+B2+C3+D3",
      "big_holder_pct": 6.6,
      "big_holder_chg": -0.02,
      "margin_chg": 12120,
      "short_chg": 75,
      "inst_ratio": 6562.6,
      "price": 11.5,
      "above_ma20": true
    },
    {
      "stock_id": "1708",
      "name": "東鹼",
      "total_score": 8,
      "score_detail": "A0+B2+C3+D3",
      "big_holder_pct": 6.2,
      "big_holder_chg": 0.29,
      "margin_chg": 3630,
      "short_chg": 113,
      "inst_ratio": 3734.1,
      "price": 49.1,
      "above_ma20": true
    }
  ],
  "sell_signals": [
    {
      "stock_id": "5347",
      "name": "世界",
      "consecutive_days": 3,
      "total_net": -22073343.0,
      "daily_nets": {
        "2026-06-03": -5658163.0,
        "2026-06-04": -7749612.0,
        "2026-06-05": -8665568.0
      },
      "price": 161.5,
      "ma20": 166.85,
      "ma60": 142.74,
      "below_ma20": true,
      "below_ma60": false
    },
    {
      "stock_id": "3036",
      "name": "文曄",
      "consecutive_days": 3,
      "total_net": -20519303.0,
      "daily_nets": {
        "2026-06-03": -6790482.0,
        "2026-06-04": -6854000.0,
        "2026-06-05": -6874821.0
      },
      "price": 281.0,
      "ma20": 282.8,
      "ma60": 244.63,
      "below_ma20": true,
      "below_ma60": false
    },
    {
      "stock_id": "3702",
      "name": "大聯大",
      "consecutive_days": 3,
      "total_net": -17145000.0,
      "daily_nets": {
        "2026-06-03": -6083000.0,
        "2026-06-04": -5522000.0,
        "2026-06-05": -5540000.0
      },
      "price": 114.5,
      "ma20": 116.5,
      "ma60": 101.6,
      "below_ma20": true,
      "below_ma60": false
    },
    {
      "stock_id": "6176",
      "name": "瑞儀",
      "consecutive_days": 3,
      "total_net": -16342262.0,
      "daily_nets": {
        "2026-06-03": -5548000.0,
        "2026-06-04": -5388000.0,
        "2026-06-05": -5406262.0
      },
      "price": 101.0,
      "ma20": 103.25,
      "ma60": 98.0,
      "below_ma20": true,
      "below_ma60": false
    },
    {
      "stock_id": "8422",
      "name": "可寧衛*",
      "consecutive_days": 3,
      "total_net": -10912000.0,
      "daily_nets": {
        "2026-06-03": -3682000.0,
        "2026-06-04": -3583000.0,
        "2026-06-05": -3647000.0
      },
      "price": 28.1,
      "ma20": 27.02,
      "ma60": 28.51,
      "below_ma20": false,
      "below_ma60": true
    },
    {
      "stock_id": "6412",
      "name": "群電",
      "consecutive_days": 3,
      "total_net": -6841000.0,
      "daily_nets": {
        "2026-06-03": -2278000.0,
        "2026-06-04": -2280000.0,
        "2026-06-05": -2283000.0
      },
      "price": 97.9,
      "ma20": 98.02,
      "ma60": 85.45,
      "below_ma20": true,
      "below_ma60": false
    },
    {
      "stock_id": "2451",
      "name": "創見",
      "consecutive_days": 3,
      "total_net": -6653000.0,
      "daily_nets": {
        "2026-06-03": -2381000.0,
        "2026-06-04": -3120000.0,
        "2026-06-05": -1152000.0
      },
      "price": 321.5,
      "ma20": 332.12,
      "ma60": 282.53,
      "below_ma20": true,
      "below_ma60": false
    },
    {
      "stock_id": "1215",
      "name": "卜蜂",
      "consecutive_days": 3,
      "total_net": -5215000.0,
      "daily_nets": {
        "2026-06-03": -1755000.0,
        "2026-06-04": -1750000.0,
        "2026-06-05": -1710000.0
      },
      "price": 119.0,
      "ma20": 132.45,
      "ma60": 139.8,
      "below_ma20": true,
      "below_ma60": true
    },
    {
      "stock_id": "8299",
      "name": "群聯",
      "consecutive_days": 3,
      "total_net": -2351910.0,
      "daily_nets": {
        "2026-06-03": -447821.0,
        "2026-06-04": -449862.0,
        "2026-06-05": -1454227.0
      },
      "price": 2450.0,
      "ma20": 2578.5,
      "ma60": 2067.0,
      "below_ma20": true,
      "below_ma60": false
    },
    {
      "stock_id": "6278",
      "name": "台表科",
      "consecutive_days": 3,
      "total_net": -1801000.0,
      "daily_nets": {
        "2026-06-03": -835000.0,
        "2026-06-04": -442000.0,
        "2026-06-05": -524000.0
      },
      "price": 206.5,
      "ma20": 220.15,
      "ma60": 157.28,
      "below_ma20": true,
      "below_ma60": false
    },
    {
      "stock_id": "9907",
      "name": "統一實",
      "consecutive_days": 3,
      "total_net": -1290042.0,
      "daily_nets": {
        "2026-06-03": -256565.0,
        "2026-06-04": -187281.0,
        "2026-06-05": -846196.0
      },
      "price": 16.65,
      "ma20": 16.24,
      "ma60": 17.41,
      "below_ma20": false,
      "below_ma60": true
    },
    {
      "stock_id": "4966",
      "name": "譜瑞-KY",
      "consecutive_days": 3,
      "total_net": -1076000.0,
      "daily_nets": {
        "2026-06-03": -214000.0,
        "2026-06-04": -143000.0,
        "2026-06-05": -719000.0
      },
      "price": 736.0,
      "ma20": 795.35,
      "ma60": 622.92,
      "below_ma20": true,
      "below_ma60": false
    },
    {
      "stock_id": "9904",
      "name": "寶成",
      "consecutive_days": 3,
      "total_net": -954120.0,
      "daily_nets": {
        "2026-06-03": -566495.0,
        "2026-06-04": -151566.0,
        "2026-06-05": -236059.0
      },
      "price": 26.45,
      "ma20": 25.89,
      "ma60": 27.17,
      "below_ma20": false,
      "below_ma60": true
    },
    {
      "stock_id": "3105",
      "name": "穩懋",
      "consecutive_days": 3,
      "total_net": -923537.0,
      "daily_nets": {
        "2026-06-03": -268539.0,
        "2026-06-04": -141276.0,
        "2026-06-05": -513722.0
      },
      "price": 483.5,
      "ma20": 504.9,
      "ma60": 458.31,
      "below_ma20": true,
      "below_ma60": false
    },
    {
      "stock_id": "6488",
      "name": "環球晶",
      "consecutive_days": 3,
      "total_net": -903658.0,
      "daily_nets": {
        "2026-06-03": -444294.0,
        "2026-06-04": -66804.0,
        "2026-06-05": -392560.0
      },
      "price": 811.0,
      "ma20": 816.7,
      "ma60": 617.33,
      "below_ma20": true,
      "below_ma60": false
    },
    {
      "stock_id": "3533",
      "name": "嘉澤",
      "consecutive_days": 3,
      "total_net": -561572.0,
      "daily_nets": {
        "2026-06-03": -71000.0,
        "2026-06-04": -317000.0,
        "2026-06-05": -173572.0
      },
      "price": 2365.0,
      "ma20": 2536.0,
      "ma60": 2369.17,
      "below_ma20": true,
      "below_ma60": true
    },
    {
      "stock_id": "2337",
      "name": "旺宏",
      "consecutive_days": 3,
      "total_net": -481000.0,
      "daily_nets": {
        "2026-06-03": -6000.0,
        "2026-06-04": -386000.0,
        "2026-06-05": -89000.0
      },
      "price": 150.0,
      "ma20": 157.7,
      "ma60": 145.26,
      "below_ma20": true,
      "below_ma60": false
    },
    {
      "stock_id": "2049",
      "name": "上銀",
      "consecutive_days": 3,
      "total_net": -367204.0,
      "daily_nets": {
        "2026-06-03": -48551.0,
        "2026-06-04": -316102.0,
        "2026-06-05": -2551.0
      },
      "price": 345.0,
      "ma20": 376.4,
      "ma60": 302.39,
      "below_ma20": true,
      "below_ma60": false
    },
    {
      "stock_id": "6781",
      "name": "AES-KY",
      "consecutive_days": 3,
      "total_net": -341188.0,
      "daily_nets": {
        "2026-06-03": -300000.0,
        "2026-06-04": -41000.0,
        "2026-06-05": -188.0
      },
      "price": 1135.0,
      "ma20": 1190.0,
      "ma60": 1101.98,
      "below_ma20": true,
      "below_ma60": false
    }
  ]
}